lucidoc/__init__.py
lucidoc/_version.py
lucidoc/docparse.py
lucidoc/docstyle.py
lucidoc/doctags.py
lucidoc/exceptions.py
lucidoc/helpers.py
lucidoc/lucidoc.py
lucidoc-0.4.4.dist-info/METADATA
lucidoc-0.4.4.dist-info/WHEEL
lucidoc-0.4.4.dist-info/entry_points.txt
lucidoc-0.4.4.dist-info/top_level.txt
lucidoc-0.4.4.dist-info/RECORD
