Metadata-Version: 2.1
Name: lucidoc
Version: 0.4.4
Summary: API documentation in Markdown
Home-page: https://github.com/databio/lucidoc/
Author: Vince Reuter
License: BSD2
Keywords: documentation,API,docs,mkdocs,autodoc
Classifier: Development Status :: 4 - Beta
Classifier: License :: OSI Approved :: BSD License
Classifier: Programming Language :: Python :: 3.7
Classifier: Programming Language :: Python :: 3.8
Classifier: Programming Language :: Python :: 3.9
Classifier: Programming Language :: Python :: 3.10
Requires-Dist: logmuse (>=0.2.7)
Requires-Dist: ubiquerg (>=0.0.5)
